ctkmessagebox3/__init__.py
ctkmessagebox3/ctkmessagebox.py
ctkmessagebox3/demo.py
ctkmessagebox3/icons/alert-icon.png
ctkmessagebox3/icons/ask-icon.png
ctkmessagebox3/icons/error-icon.png
ctkmessagebox3/icons/info-icon.png
ctkmessagebox3/icons/ok-icon.png
ctkmessagebox3-3.0.4.dist-info/LICENSE
ctkmessagebox3-3.0.4.dist-info/METADATA
ctkmessagebox3-3.0.4.dist-info/WHEEL
ctkmessagebox3-3.0.4.dist-info/RECORD
