Metadata-Version: 2.3
Name: ctkmessagebox3
Version: 3.0.4
Summary: A repaired and improved version of CTkMessageBox package for CustomTkinter.
Author: jacky wu
Author-email: jacky.wucheng@gmail.com
Requires-Python: >=3.12
Classifier: Programming Language :: Python :: 3
Classifier: License :: OSI Approved :: MIT License
Classifier: Operating System :: OS Independent
Requires-Dist: customtkinter (>=5.2.2,<6.0.0)
Requires-Dist: pillow (>=11.3.0,<12.0.0)
Project-URL: Homepage, https://github.com/jackywu/ctkmessagebox
Project-URL: Issues, https://github.com/jackywu/ctkmessagebox/issues
